mce/__init__.py
mce/bdd.py
mce/demos.py
mce/draw.py
mce/foo.dot
mce/infer.py
mce/nx.py
mce/order.py
mce/policy3.py
mce/preimage.py
mce/sample.py
mce/spec.py
mce/test_scenarios.py
mce_spec_inference-0.1.0.dist-info/LICENSE
mce_spec_inference-0.1.0.dist-info/WHEEL
mce_spec_inference-0.1.0.dist-info/METADATA
mce_spec_inference-0.1.0.dist-info/RECORD
